{
  "benchmark_id": "rq3_openstack_inventory_probe_v1_20260319",
  "benchmark_kind": "single_case_local_probe",
  "purpose": "Probe whether a pre-mismatch host-detail anchor can support an OpenStack inventory-drift slot without collapsing into direct taxonomy matching.",
  "contract_path": "/Users/peihanye/Desktop/Projects/NuSy-Edge/experiments/thesis_rebuild_20260315/rq3_rebuild_v1/configs/contract_v1_20260318.json",
  "formal_small_ready": false,
  "paid_api_allowed": false,
  "noise_levels": [
    0.0,
    1.0
  ],
  "cases": [
    {
      "dataset": "OpenStack",
      "case_id": "openstack_win_20",
      "source": "benchmark_v2",
      "gt_family_id": "OPENSTACK_INSTANCE_STATE_DRIFT",
      "gt_action_id": "OPENSTACK_RESYNC_INSTANCE_INVENTORY",
      "eligibility_note": "Inventory-drift probe anchored to the host-detail poll immediately before the scheduler reports an InstanceList mismatch.",
      "selected_alert_clean": "nova-api.log.2017-05-14_21:27:04 2017-05-14 19:50:55.929 25746 INFO nova.osapi_compute.wsgi.server [req-8ee4e559-c451-40c7-b725-596aeea91d30 113d3a99c3da401fbd62cc2caa5b96d2 54fadb412c4e40cdbaed9335e4c35a9e - - -] 10.11.10.1 \"GET /v2/54fadb412c4e40cdbaed9335e4c35a9e/servers/detail HTTP/1.1\" status: 200 len: 1893 time: 0.2438881",
      "shared_context_clean": "nova-api.log.2017-05-14_21:27:04 2017-05-14 19:50:54.406 25746 INFO nova.osapi_compute.wsgi.server [req-bcb19162-72f0-4df9-840b-600a4c62cbb3 113d3a99c3da401fbd62cc2caa5b96d2 54fadb412c4e40cdbaed9335e4c35a9e - - -] 10.11.10.1 \"GET /v2/54fadb412c4e40cdbaed9335e4c35a9e/servers/detail HTTP/1.1\" status: 200 len: 1893 time: 0.2605600\nnova-api.log.2017-05-14_21:27:04 2017-05-14 19:50:55.681 25746 INFO nova.osapi_compute.wsgi.server [req-d1b62af5-3dd5-4f42-be6a-a9a127a72f4f 113d3a99c3da401fbd62cc2caa5b96d2 54fadb412c4e40cdbaed9335e4c35a9e - - -] 10.11.10.1 \"GET /v2/54fadb412c4e40cdbaed9335e4c35a9e/servers/detail HTTP/1.1\" status: 200 len: 1893 time: 0.2684741",
      "provenance": {
        "ground_truth_root_cause_template": "couldn't obtain the vcpu count from domain id: <*>, exception: Requested operation is not valid: cpu affinity is not supported",
        "ground_truth_template": "couldn't obtain the vcpu count from domain id: <*>, exception: Requested operation is not valid: cpu affinity is not supported",
        "reason": ""
      },
      "noise_views": {
        "0.0": {
          "noise": 0.0,
          "selected_alert": "nova-api.log.2017-05-14_21:27:04 2017-05-14 19:50:55.929 25746 INFO nova.osapi_compute.wsgi.server [req-8ee4e559-c451-40c7-b725-596aeea91d30 113d3a99c3da401fbd62cc2caa5b96d2 54fadb412c4e40cdbaed9335e4c35a9e - - -] 10.11.10.1 \"GET /v2/54fadb412c4e40cdbaed9335e4c35a9e/servers/detail HTTP/1.1\" status: 200 len: 1893 time: 0.2438881",
          "context_text": "nova-api.log.2017-05-14_21:27:04 2017-05-14 19:50:54.406 25746 INFO nova.osapi_compute.wsgi.server [req-bcb19162-72f0-4df9-840b-600a4c62cbb3 113d3a99c3da401fbd62cc2caa5b96d2 54fadb412c4e40cdbaed9335e4c35a9e - - -] 10.11.10.1 \"GET /v2/54fadb412c4e40cdbaed9335e4c35a9e/servers/detail HTTP/1.1\" status: 200 len: 1893 time: 0.2605600\nnova-api.log.2017-05-14_21:27:04 2017-05-14 19:50:55.681 25746 INFO nova.osapi_compute.wsgi.server [req-d1b62af5-3dd5-4f42-be6a-a9a127a72f4f 113d3a99c3da401fbd62cc2caa5b96d2 54fadb412c4e40cdbaed9335e4c35a9e - - -] 10.11.10.1 \"GET /v2/54fadb412c4e40cdbaed9335e4c35a9e/servers/detail HTTP/1.1\" status: 200 len: 1893 time: 0.2684741",
          "rag_references": [
            {
              "reference_id": "supplemental:rq3_test_set_enriched:openstack_47",
              "score": 25.2442,
              "lexical": 21.2442,
              "action_id": "OPENSTACK_RESYNC_INSTANCE_INVENTORY",
              "family_id": "OPENSTACK_INSTANCE_STATE_DRIFT",
              "text": "Historical incident snippet\nPrimary signal: nova-scheduler.log.1.2017-05-16_13:53:08 2017-05-16 00:13:09.162 25998 INFO nova.scheduler.host_manager [req-c34edf86-25ac-4c79-ab19-9ea9caa4eddf - - - - -] The instance sync for host 'cp-1.slowvm1.tcloud-pg0.utah.cloudlab.us' did not match. Re-created its InstanceList.\nNearby context: nova-api.log.1.2017-05-16_13:53:08 2017-05-16 00:13:07.958 25746 INFO nova.osapi_compute.wsgi.server [req-ea4a360f-b853-46fe-af72-7db91c3346ad 113d3a99c3da401fbd62cc2caa5b96d2 54fadb412c4e40cdbaed9335e4c35a9e - - -] 10.11.10.1 \"GET /v2/54fadb412c4e40cdbaed9335e4c35a9e/servers/detail HTTP/1.1\" status: 200 len: 1893 time: 0.2724142\nnova-compute.log.1.2017-05-16_13:55:31 2017-05-16 00:13:09.118 2931 INFO nova.compute.ma"
            },
            {
              "reference_id": "supplemental:rq3_test_set_enriched:openstack_48",
              "score": 25.2386,
              "lexical": 21.2386,
              "action_id": "OPENSTACK_RESYNC_INSTANCE_INVENTORY",
              "family_id": "OPENSTACK_INSTANCE_STATE_DRIFT",
              "text": "Historical incident snippet\nPrimary signal: nova-api.log.1.2017-05-16_13:53:08 2017-05-16 00:09:08.029 25743 INFO nova.api.openstack.compute.server_external_events [req-2f1a8f6f-b2fc-48af-92c3-8a37d40f54dc f7b8d1f1d4d44643b07fa10ca7d021fb e9746973ac574c6b8a9e8857f56a7608 - - -] Creating event network-vif-plugged:1bb8c7a3-effa-4568-8cf7-2b9a55011df9 for instance 70c1714b-c11b-4c88-b300-239afe1f5ff8\nNearby context: nova-api.log.1.2017-05-16_13:53:08 2017-05-16 00:09:06.497 25746 INFO nova.osapi_compute.wsgi.server [req-94248553-16cd-4c90-944b-22c39d61951c 113d3a99c3da401fbd62cc2caa5b96d2 54fadb412c4e40cdbaed9335e4c35a9e - - -] 10.11.10.1 \"GET /v2/54fadb412c4e40cdbaed9335e4c35a9e/servers/detail HTTP/1.1\" status: 200 len: 1893 time: 0.2661738\nnova-api.log.1.2017-05-16_13:53:08 2017-05-16 00:09:07.779 25746 INFO nova.osapi_compute"
            }
          ],
          "agent_references": [
            {
              "reference_id": "supplemental:rq3_test_set_enriched:openstack_47",
              "score": 25.2442,
              "lexical": 21.2442,
              "action_id": "OPENSTACK_RESYNC_INSTANCE_INVENTORY",
              "family_id": "OPENSTACK_INSTANCE_STATE_DRIFT",
              "text": "Historical incident snippet\nPrimary signal: nova-scheduler.log.1.2017-05-16_13:53:08 2017-05-16 00:13:09.162 25998 INFO nova.scheduler.host_manager [req-c34edf86-25ac-4c79-ab19-9ea9caa4eddf - - - - -] The instance sync for host 'cp-1.slowvm1.tcloud-pg0.utah.cloudlab.us' did not match. Re-created its InstanceList.\nNearby context: nova-api.log.1.2017-05-16_13:53:08 2017-05-16 00:13:07.958 25746 INFO nova.osapi_compute.wsgi.server [req-ea4a360f-b853-46fe-af72-7db91c3346ad 113d3a99c3da401fbd62cc2caa5b96d2 54fadb412c4e40cdbaed9335e4c35a9e - - -] 10.11.10.1 \"GET /v2/54fadb412c4e40cdbaed9335e4c35a9e/servers/detail HTTP/1.1\" status: 200 len: 1893 time: 0.2724142\nnova-compute.log.1.2017-05-16_13:55:31 2017-05-16 00:13:09.118 2931 INFO nova.compute.ma"
            },
            {
              "reference_id": "supplemental:rq3_test_set_enriched:openstack_48",
              "score": 25.2386,
              "lexical": 21.2386,
              "action_id": "OPENSTACK_RESYNC_INSTANCE_INVENTORY",
              "family_id": "OPENSTACK_INSTANCE_STATE_DRIFT",
              "text": "Historical incident snippet\nPrimary signal: nova-api.log.1.2017-05-16_13:53:08 2017-05-16 00:09:08.029 25743 INFO nova.api.openstack.compute.server_external_events [req-2f1a8f6f-b2fc-48af-92c3-8a37d40f54dc f7b8d1f1d4d44643b07fa10ca7d021fb e9746973ac574c6b8a9e8857f56a7608 - - -] Creating event network-vif-plugged:1bb8c7a3-effa-4568-8cf7-2b9a55011df9 for instance 70c1714b-c11b-4c88-b300-239afe1f5ff8\nNearby context: nova-api.log.1.2017-05-16_13:53:08 2017-05-16 00:09:06.497 25746 INFO nova.osapi_compute.wsgi.server [req-94248553-16cd-4c90-944b-22c39d61951c 113d3a99c3da401fbd62cc2caa5b96d2 54fadb412c4e40cdbaed9335e4c35a9e - - -] 10.11.10.1 \"GET /v2/54fadb412c4e40cdbaed9335e4c35a9e/servers/detail HTTP/1.1\" status: 200 len: 1893 time: 0.2661738\nnova-api.log.1.2017-05-16_13:53:08 2017-05-16 00:09:07.779 25746 INFO nova.osapi_compute"
            }
          ],
          "graph_evidence": {
            "summary_lines": [
              "Historical causal cue: scheduler host_manager req host tcloud utah -> scheduler host_manager req instance sync host (relation=symbolic_prior).",
              "Historical causal cue: wsgi server get len metadata ipip -> wsgi server req get len metadata (relation=symbolic_prior)."
            ],
            "matched_edges": [
              {
                "source_template": "nova.scheduler.host_manager [req-<UUID> - - - - -] Successfully synced instances from host 'cp-<NUM>.slowvm<NUM>.tcloud-pg<NUM>.utah.cloudlab.us'.",
                "target_template": "nova.scheduler.host_manager [req-<UUID> - - - - -] The instance sync for host 'cp-<NUM>.slowvm<NUM>.tcloud-pg<NUM>.utah.cloudlab.us' did not match. Re-created its InstanceList.",
                "relation": "symbolic_prior",
                "weight": 0.55,
                "score": 42.8825,
                "query_source_overlap": 2,
                "query_target_overlap": 2,
                "reference_source_overlap": 8,
                "reference_target_overlap": 18
              },
              {
                "source_template": "nova.metadata.wsgi.server [-] <IP>,<IP> \"GET /latest/meta-data/local-hostname HTTP/<NUM>.<NUM>\" status: <NUM> len: <NUM> time: <NUM>.<NUM>",
                "target_template": "nova.metadata.wsgi.server [req-<UUID> - - - - -] <IP>,<IP> \"GET /latest/meta-data/security-groups HTTP/<NUM>.<NUM>\" status: <NUM> len: <NUM> time: <NUM>.<NUM>",
                "relation": "symbolic_prior",
                "weight": 1.0647,
                "score": 36.3597,
                "query_source_overlap": 8,
                "query_target_overlap": 9,
                "reference_source_overlap": 8,
                "reference_target_overlap": 9
              }
            ]
          }
        },
        "1.0": {
          "noise": 1.0,
          "selected_alert": "nova-api.log.2017-05-14_21:27:04 2017-05-14 19:50:55.929 25746 INFO nova.osapi_compute.wsgi.control [req-8ee4e559-c451-40c7-b725-596aeea91d30 113d3a99c3da401fbd62cc2caa5b96d2 54fadb412c4e40cdbaed9335e4c35a9e - - -] 10.11.10.1 \"LIST /v2/54fadb412c4e40cdbaed9335e4c35a9e/control-plane-cache-view HTTP/1.1\" status=200 len: 1893 time: 0.2438881",
          "context_text": "nova-api.log.2017-05-14_21:27:04 2017-05-14 19:50:54.406 25746 INFO nova.osapi_compute.wsgi.control [req-bcb19162-72f0-4df9-840b-600a4c62cbb3 113d3a99c3da401fbd62cc2caa5b96d2 54fadb412c4e40cdbaed9335e4c35a9e - - -] 10.11.10.1 \"LIST /v2/54fadb412c4e40cdbaed9335e4c35a9e/control-plane-cache-view HTTP/1.1\" status=200 len: 1893 time: 0.2605600\nnova-api.log.2017-05-14_21:27:04 2017-05-14 19:50:55.681 25746 INFO nova.osapi_compute.wsgi.control [req-d1b62af5-3dd5-4f42-be6a-a9a127a72f4f 113d3a99c3da401fbd62cc2caa5b96d2 54fadb412c4e40cdbaed9335e4c35a9e - - -] 10.11.10.1 \"LIST /v2/54fadb412c4e40cdbaed9335e4c35a9e/control-plane-cache-view HTTP/1.1\" status=200 len: 1893 time: 0.2684741",
          "rag_references": [
            {
              "reference_id": "supplemental:rq3_test_set_enriched:openstack_47",
              "score": 25.2442,
              "lexical": 21.2442,
              "action_id": "OPENSTACK_RESYNC_INSTANCE_INVENTORY",
              "family_id": "OPENSTACK_INSTANCE_STATE_DRIFT",
              "text": "Historical incident snippet\nPrimary signal: nova-scheduler.log.1.2017-05-16_13:53:08 2017-05-16 00:13:09.162 25998 INFO nova.scheduler.host_manager [req-c34edf86-25ac-4c79-ab19-9ea9caa4eddf - - - - -] The instance sync for host 'cp-1.slowvm1.tcloud-pg0.utah.cloudlab.us' did not match. Re-created its InstanceList.\nNearby context: nova-api.log.1.2017-05-16_13:53:08 2017-05-16 00:13:07.958 25746 INFO nova.osapi_compute.wsgi.server [req-ea4a360f-b853-46fe-af72-7db91c3346ad 113d3a99c3da401fbd62cc2caa5b96d2 54fadb412c4e40cdbaed9335e4c35a9e - - -] 10.11.10.1 \"GET /v2/54fadb412c4e40cdbaed9335e4c35a9e/servers/detail HTTP/1.1\" status: 200 len: 1893 time: 0.2724142\nnova-compute.log.1.2017-05-16_13:55:31 2017-05-16 00:13:09.118 2931 INFO nova.compute.ma"
            },
            {
              "reference_id": "supplemental:rq3_test_set_enriched:openstack_48",
              "score": 25.2386,
              "lexical": 21.2386,
              "action_id": "OPENSTACK_RESYNC_INSTANCE_INVENTORY",
              "family_id": "OPENSTACK_INSTANCE_STATE_DRIFT",
              "text": "Historical incident snippet\nPrimary signal: nova-api.log.1.2017-05-16_13:53:08 2017-05-16 00:09:08.029 25743 INFO nova.api.openstack.compute.server_external_events [req-2f1a8f6f-b2fc-48af-92c3-8a37d40f54dc f7b8d1f1d4d44643b07fa10ca7d021fb e9746973ac574c6b8a9e8857f56a7608 - - -] Creating event network-vif-plugged:1bb8c7a3-effa-4568-8cf7-2b9a55011df9 for instance 70c1714b-c11b-4c88-b300-239afe1f5ff8\nNearby context: nova-api.log.1.2017-05-16_13:53:08 2017-05-16 00:09:06.497 25746 INFO nova.osapi_compute.wsgi.server [req-94248553-16cd-4c90-944b-22c39d61951c 113d3a99c3da401fbd62cc2caa5b96d2 54fadb412c4e40cdbaed9335e4c35a9e - - -] 10.11.10.1 \"GET /v2/54fadb412c4e40cdbaed9335e4c35a9e/servers/detail HTTP/1.1\" status: 200 len: 1893 time: 0.2661738\nnova-api.log.1.2017-05-16_13:53:08 2017-05-16 00:09:07.779 25746 INFO nova.osapi_compute"
            }
          ],
          "agent_references": [
            {
              "reference_id": "supplemental:rq3_test_set_enriched:openstack_47",
              "score": 25.2442,
              "lexical": 21.2442,
              "action_id": "OPENSTACK_RESYNC_INSTANCE_INVENTORY",
              "family_id": "OPENSTACK_INSTANCE_STATE_DRIFT",
              "text": "Historical incident snippet\nPrimary signal: nova-scheduler.log.1.2017-05-16_13:53:08 2017-05-16 00:13:09.162 25998 INFO nova.scheduler.host_manager [req-c34edf86-25ac-4c79-ab19-9ea9caa4eddf - - - - -] The instance sync for host 'cp-1.slowvm1.tcloud-pg0.utah.cloudlab.us' did not match. Re-created its InstanceList.\nNearby context: nova-api.log.1.2017-05-16_13:53:08 2017-05-16 00:13:07.958 25746 INFO nova.osapi_compute.wsgi.server [req-ea4a360f-b853-46fe-af72-7db91c3346ad 113d3a99c3da401fbd62cc2caa5b96d2 54fadb412c4e40cdbaed9335e4c35a9e - - -] 10.11.10.1 \"GET /v2/54fadb412c4e40cdbaed9335e4c35a9e/servers/detail HTTP/1.1\" status: 200 len: 1893 time: 0.2724142\nnova-compute.log.1.2017-05-16_13:55:31 2017-05-16 00:13:09.118 2931 INFO nova.compute.ma"
            },
            {
              "reference_id": "supplemental:rq3_test_set_enriched:openstack_48",
              "score": 25.2386,
              "lexical": 21.2386,
              "action_id": "OPENSTACK_RESYNC_INSTANCE_INVENTORY",
              "family_id": "OPENSTACK_INSTANCE_STATE_DRIFT",
              "text": "Historical incident snippet\nPrimary signal: nova-api.log.1.2017-05-16_13:53:08 2017-05-16 00:09:08.029 25743 INFO nova.api.openstack.compute.server_external_events [req-2f1a8f6f-b2fc-48af-92c3-8a37d40f54dc f7b8d1f1d4d44643b07fa10ca7d021fb e9746973ac574c6b8a9e8857f56a7608 - - -] Creating event network-vif-plugged:1bb8c7a3-effa-4568-8cf7-2b9a55011df9 for instance 70c1714b-c11b-4c88-b300-239afe1f5ff8\nNearby context: nova-api.log.1.2017-05-16_13:53:08 2017-05-16 00:09:06.497 25746 INFO nova.osapi_compute.wsgi.server [req-94248553-16cd-4c90-944b-22c39d61951c 113d3a99c3da401fbd62cc2caa5b96d2 54fadb412c4e40cdbaed9335e4c35a9e - - -] 10.11.10.1 \"GET /v2/54fadb412c4e40cdbaed9335e4c35a9e/servers/detail HTTP/1.1\" status: 200 len: 1893 time: 0.2661738\nnova-api.log.1.2017-05-16_13:53:08 2017-05-16 00:09:07.779 25746 INFO nova.osapi_compute"
            }
          ],
          "graph_evidence": {
            "summary_lines": [
              "Historical causal cue: scheduler host_manager req host tcloud utah -> scheduler host_manager req instance sync host (relation=symbolic_prior).",
              "Historical causal cue: wsgi server get len metadata ipip -> wsgi server req get len metadata (relation=symbolic_prior)."
            ],
            "matched_edges": [
              {
                "source_template": "nova.scheduler.host_manager [req-<UUID> - - - - -] Successfully synced instances from host 'cp-<NUM>.slowvm<NUM>.tcloud-pg<NUM>.utah.cloudlab.us'.",
                "target_template": "nova.scheduler.host_manager [req-<UUID> - - - - -] The instance sync for host 'cp-<NUM>.slowvm<NUM>.tcloud-pg<NUM>.utah.cloudlab.us' did not match. Re-created its InstanceList.",
                "relation": "symbolic_prior",
                "weight": 0.55,
                "score": 42.8825,
                "query_source_overlap": 2,
                "query_target_overlap": 2,
                "reference_source_overlap": 8,
                "reference_target_overlap": 18
              },
              {
                "source_template": "nova.metadata.wsgi.server [-] <IP>,<IP> \"GET /latest/meta-data/local-hostname HTTP/<NUM>.<NUM>\" status: <NUM> len: <NUM> time: <NUM>.<NUM>",
                "target_template": "nova.metadata.wsgi.server [req-<UUID> - - - - -] <IP>,<IP> \"GET /latest/meta-data/security-groups HTTP/<NUM>.<NUM>\" status: <NUM> len: <NUM> time: <NUM>.<NUM>",
                "relation": "symbolic_prior",
                "weight": 1.0647,
                "score": 36.3597,
                "query_source_overlap": 8,
                "query_target_overlap": 9,
                "reference_source_overlap": 8,
                "reference_target_overlap": 9
              }
            ]
          }
        }
      }
    }
  ]
}